XStatic_multiDownload-20110717.1-py3.13-nspkg.pth
xstatic/pkg/jquery_multi_download/__init__.py
xstatic/pkg/jquery_multi_download/__init__.py~
xstatic/pkg/jquery_multi_download/data/jquery.multiDownload.js
xstatic_multidownload-20110717.1.dist-info/METADATA
xstatic_multidownload-20110717.1.dist-info/WHEEL
xstatic_multidownload-20110717.1.dist-info/namespace_packages.txt
xstatic_multidownload-20110717.1.dist-info/top_level.txt
xstatic_multidownload-20110717.1.dist-info/RECORD
