Metadata-Version: 2.4
Name: XStatic-multiDownload
Version: 20110717.1
Summary: multiDownload 20110717 (XStatic packaging standard)
Home-page: http://biesiad.rushbean.com/multidownload/
Maintainer: Reimar Bauer
Maintainer-email: rb.proj@googlemail.com
License: (same as multiDownload)
Keywords: jquery_multi_download xstatic
Platform: any
Dynamic: description
Dynamic: home-page
Dynamic: keywords
Dynamic: license
Dynamic: maintainer
Dynamic: maintainer-email
Dynamic: platform
Dynamic: summary
